tunga/__init__.py
tunga/extraction/__init__.py
tunga/extraction/extraction.py
tunga/machine_learning/__init__.py
tunga/machine_learning/keyword_extraction/__init__.py
tunga/machine_learning/keyword_extraction/rake.py
tunga/machine_learning/ner/__init__.py
tunga/machine_learning/ner/bert.py
tunga/machine_learning/sentiment_analysis/__init__.py
tunga/machine_learning/sentiment_analysis/bert_sentiment.py
tunga/machine_learning/sentiment_analysis/product_sentiment.py
tunga/machine_learning/summarization/__init__.py
tunga/machine_learning/summarization/summarizer.py
tunga/machine_learning/summarization/punkt/__init__.py
tunga/machine_learning/topic_modelling/__init__.py
tunga/machine_learning/topic_modelling/topic_modeller.py
tunga/machine_learning/translation/__init__.py
tunga/machine_learning/translation/google_translation.py
tunga/machine_learning/translation/tunga_translation.py
tunga/preprocessing/__init__.py
tunga/preprocessing/normalization.py
tunga/retrieval/Twitter.py
tunga/retrieval/__init__.py
tunga-1.0.88.dist-info/LICENSE
tunga-1.0.88.dist-info/METADATA
tunga-1.0.88.dist-info/WHEEL
tunga-1.0.88.dist-info/top_level.txt
tunga-1.0.88.dist-info/RECORD
