Metadata-Version: 2.1
Name: tunga
Version: 1.0.88
Summary: Tunga Core Library
Home-page: https://github.com/tahtaciburak/tunga
Author: Burak TAHTACI
Author-email: tahtaiburak@gmail.com
License: UNKNOWN
Platform: UNKNOWN
Classifier: Programming Language :: Python :: 3
Classifier: License :: OSI Approved :: MIT License
Classifier: Operating System :: OS Independent
Requires-Python: >=3.6
Requires-Dist: pandas
Requires-Dist: bs4
Requires-Dist: tweepy
Requires-Dist: TurkishStemmer
Requires-Dist: grpcio
Requires-Dist: price-parser
Requires-Dist: zemberek-grpc
Requires-Dist: multi-rake
Requires-Dist: sklearn
Requires-Dist: pytorch-transformers (==1.2.0)
Requires-Dist: transformers (==2.9.0)
